planet_crs_registry_client/__init__.py
planet_crs_registry_client/client.py
planet_crs_registry_client/errors.py
planet_crs_registry_client/py.typed
planet_crs_registry_client/types.py
planet_crs_registry_client/api/__init__.py
planet_crs_registry_client/api/browse_by_solar_body/__init__.py
planet_crs_registry_client/api/browse_by_solar_body/get_solar_bodies_ws_solar_bodies_get.py
planet_crs_registry_client/api/browse_by_solar_body/get_solar_body_count_ws_solar_bodies_solar_body_count_get.py
planet_crs_registry_client/api/browse_by_solar_body/get_solar_body_ws_solar_bodies_solar_body_get.py
planet_crs_registry_client/api/browse_by_solar_body/get_wkt_body_ws_solar_bodies_solar_body_wkt_id_get.py
planet_crs_registry_client/api/browse_by_solar_body/solar_bodies_count_ws_solar_bodies_count_get.py
planet_crs_registry_client/api/browse_by_wkt/__init__.py
planet_crs_registry_client/api/browse_by_wkt/get_wkt_ws_wkts_wkt_id_get.py
planet_crs_registry_client/api/browse_by_wkt/get_wkts_ws_wkts_get.py
planet_crs_registry_client/api/browse_by_wkt/wkts_count_ws_wkts_count_get.py
planet_crs_registry_client/api/browse_by_wkt_version/__init__.py
planet_crs_registry_client/api/browse_by_wkt_version/get_version_ws_versions_version_id_get.py
planet_crs_registry_client/api/browse_by_wkt_version/get_versions_ws_versions_get.py
planet_crs_registry_client/api/browse_by_wkt_version/get_wkt_version_ws_versions_version_id_wkt_id_get.py
planet_crs_registry_client/api/browse_by_wkt_version/version_count_ws_versions_version_id_count_get.py
planet_crs_registry_client/api/ogc_bridge/__init__.py
planet_crs_registry_client/api/ogc_bridge/get_iau_gml_ws_iau_iau_version_code_get.py
planet_crs_registry_client/api/ogc_bridge/get_iau_versions_ws_iau_get.py
planet_crs_registry_client/api/ogc_bridge/get_iau_wkts_ws_iau_iau_version_get.py
planet_crs_registry_client/api/search/__init__.py
planet_crs_registry_client/api/search/search_count_ws_search_count_get.py
planet_crs_registry_client-0.1.0.dist-info/LICENSE
planet_crs_registry_client-0.1.0.dist-info/METADATA
planet_crs_registry_client-0.1.0.dist-info/WHEEL
planet_crs_registry_client-0.1.0.dist-info/top_level.txt
planet_crs_registry_client-0.1.0.dist-info/RECORD
