Metadata-Version: 2.1
Name: planet-crs-registry-client
Version: 0.1.0
Summary: A client library for accessing planet_crs_registry
Author-email: "Dr. Andrew Annex" <ama6fy@virginia.edu>
License: MIT License
Project-URL: Repository, https://github.com/AndrewAnnex/planet-crs-registry-client.git
Keywords: CRS,planetary,REST
Classifier: Development Status :: 3 - Alpha
Classifier: Programming Language :: Python :: 3.10
Classifier: Programming Language :: Python :: 3.11
Classifier: Programming Language :: Python :: 3.12
Classifier: Intended Audience :: Science/Research
Classifier: Topic :: Scientific/Engineering
Classifier: Topic :: Scientific/Engineering :: GIS
Requires-Python: >=3.9
License-File: LICENSE
Requires-Dist: httpx<0.28.0,>=0.20.0
Requires-Dist: attrs>=21.3.0
Requires-Dist: python-dateutil<3.0.0,>=2.8.0
